myPythonLibrary/Printer.py
myPythonLibrary/Struct.py
myPythonLibrary/SubprocessManager.py
myPythonLibrary/Test.py
myPythonLibrary/__init__.py
myPythonLibrary/__init__.py.py
myPythonLibrary/get_next_pypi_version.py
myPythonLibrary/mat_vec_tools.py
myPythonLibrary/print_tools.py
mypythonlibrary-2025.12.12.data/scripts/__init__.py.py
mypythonlibrary-2025.12.12.data/scripts/get_next_pypi_version.py
mypythonlibrary-2025.12.12.dist-info/licenses/LICENSE
mypythonlibrary-2025.12.12.dist-info/METADATA
mypythonlibrary-2025.12.12.dist-info/WHEEL
mypythonlibrary-2025.12.12.dist-info/top_level.txt
mypythonlibrary-2025.12.12.dist-info/RECORD
